regex_tester/__init__.py
regex_tester/cli.py
regex_tester/gui.py
regex_validator-1.0.0.dist-info/licenses/LICENSE
regex_validator-1.0.0.dist-info/METADATA
regex_validator-1.0.0.dist-info/WHEEL
regex_validator-1.0.0.dist-info/entry_points.txt
regex_validator-1.0.0.dist-info/top_level.txt
regex_validator-1.0.0.dist-info/RECORD
