Metadata-Version: 2.4
Name: regex-validator
Version: 1.0.0
Summary: CLI and GUI tool to test regular expressions
Home-page: https://github.com/vishnugopalpg/utils/regex-tester
Author: Vishnu Gopal PG
License: MIT
Classifier: Programming Language :: Python :: 3
Classifier: License :: OSI Approved :: MIT License
Classifier: Operating System :: OS Independent
Requires-Python: >=3.7
License-File: LICENSE
Dynamic: license-file
